{
  "title": "Click Temperature 2025 — Why Some Ads Convert Instantly & Others Fail Even With the Same Audience",
  "slug": "click-temperature-2025-ad-conversion-psychology-framework",
  "description": "A 2025 framework explaining how audience click temperature affects ad performance, conversion readiness, and ROI across Google Ads, Meta Ads, and Performance Marketing.",
  "content": "<!DOCTYPE html>\n<html lang=\"en\">\n<head>\n\n<title>Click Temperature 2025 — Why Some Ads Convert Instantly & Others Fail Even With the Same Audience</title>\n\n<meta name=\"description\" content=\"A 2025 framework explaining how audience click temperature affects ad performance, conversion readiness, and ROI across Google Ads, Meta Ads, SEO and performance marketing.\">\n\n<meta name=\"keywords\" content=\"click temperature 2025, ad psychology, conversion readiness 2025, google ads optimization, meta ads strategy, performance marketing trends\">\n\n<meta property=\"og:title\" content=\"Click Temperature 2025 — Why Some Ads Convert Instantly & Others Fail Even With the Same Audience\">\n<meta property=\"og:description\" content=\"Understanding click temperature helps brands engineer higher conversion rates across Google Ads, Meta Ads, SEO, and landing pages.\">\n<meta property=\"og:type\" content=\"article\">\n<meta property=\"og:image\" content=\"COVER_IMAGE_URL\">\n<meta property=\"og:url\" content=\"https://yourdomain.com/blog/click-temperature-2025-ad-conversion-psychology-framework\">\n<meta property=\"article:section\" content=\"Digital Marketing 360\">\n\n<script type=\"application/ld+json\">\n{\n \"@context\": \"https://schema.org\",\n \"@type\": \"Article\",\n \"headline\": \"Click Temperature 2025 — Why Some Ads Convert Instantly & Others Fail Even With the Same Audience\",\n \"description\": \"A deep 2025 guide explaining how click temperature influences conversion rates, cost per lead, and ad ROI across digital channels.\",\n \"articleSection\": \"Digital Marketing 360\",\n \"author\": { \"@type\": \"Person\", \"name\": \"BeetleBulbs\" },\n \"publisher\": {\n   \"@type\": \"Organization\",\n   \"name\": \"BeetleBulbs\",\n   \"logo\": { \"@type\": \"ImageObject\", \"url\": \"YOUR_LOGO_URL\" }\n },\n \"datePublished\": \"2025-10-15\"\n}\n</script>\n\n<style>\n.diagram-box {\n background:var(--bb-bg,#f7f7f7);\n color:var(--bb-text,#111);\n padding:14px;\n border-radius:6px;\n font-family:monospace;\n white-space:pre;\n overflow-x:auto;\n font-size:14px;\n line-height:1.6;\n}\n:root { --bb-bg:#f7f7f7; --bb-text:#111; }\n.dark { --bb-bg:#1a1a1a; --bb-text:#e6e6e6; }\n@media(max-width:640px){\n .diagram-box { font-size:13px; padding:10px; }\n}\n</style>\n\n</head>\n<body>\n\n<div style=\"margin-bottom:18px;font-size:14px;color:#555;\">\n Category: <strong>Digital Marketing 360</strong>\n</div>\n\n<h1>Click Temperature 2025 — Why Some Ads Convert Instantly & Others Fail Even With the Same Audience</h1>\n\n<h2>Short Description</h2>\n<p>A 2025 framework explaining how audience click temperature affects ad performance, conversion readiness, and ROI across Google Ads, Meta Ads, and Performance Marketing.</p>\n\n<h2>Introduction</h2>\n<p>Marketers spend money on traffic, but forget one critical truth:  \n<strong>Every click has a temperature.</strong></p>\n\n<p>Two users, same age group, same interest, same location —  \none converts instantly and the other doesn’t even stay 3 seconds.</p>\n\n<p>Why?  \nBecause every user lands with a different <strong>conversion temperature</strong> — mentally, emotionally, economically.</p>\n\n<h2>The Click Temperature Spectrum (2025 Model)</h2>\n\n<div class=\"diagram-box\">\n+--------------------------------------------------------------+\n|                    CLICK TEMPERATURE MODEL — 2025            |\n+--------------------------------------------------------------+\n|  HOT CLICKS                                                   |\n|  - high intent                                                |\n|  - solution-aware                                             |\n|  - ready to take action                                       |\n+--------------------------------------------------------------+\n|  WARM CLICKS                                                  |\n|  - problem-aware                                              |\n|  - exploring options                                          |\n|  - needs reassurance                                          |\n+--------------------------------------------------------------+\n|  COLD CLICKS                                                  |\n|  - unaware                                                    |\n|  - not evaluating                                             |\n|  - low urgency                                                |\n+--------------------------------------------------------------+\n</div>\n\n<p>Most ads fail because brands treat all three clicks the same.</p>\n\n<h2>HOT Clicks (High Intent)</h2>\n<p>These users convert fast — if your landing page meets expectations.</p>\n\n<ul>\n <li>search ads (Google intent-based)</li>\n <li>brand keyword campaigns</li>\n <li>retargeting ads</li>\n</ul>\n\n<h2>WARM Clicks (Medium Intent)</h2>\n<p>These users need structured clarity + trust signals.</p>\n\n<ul>\n <li>competitor comparison pages</li>\n <li>structured landing page content</li>\n <li>emotion-based reassurance</li>\n</ul>\n\n<h2>COLD Clicks (Low Intent)</h2>\n<p>These users don’t convert immediately — but they store impressions.</p>\n\n<ul>\n <li>top-of-funnel social ads</li>\n <li>explainer videos</li>\n <li>brand storytelling + value ads</li>\n</ul>\n\n<h2>Click Path Clarity Framework (Text Diagram)</h2>\n\n<div class=\"diagram-box\">\nCOLD → WARM → HOT → ACTION\n  |        |        |\n Awareness Trust   Intent\n</div>\n\n<p>Most agencies only optimize for HOT clicks.  \nElite 2025 marketing optimizes **all three temperatures**.</p>\n\n<h2>Digital Channel Breakdown</h2>\n\n<h3>Google Ads</h3>\n<p>Search ads = HOT  \nDisplay ads = COLD  \nYouTube = COLD → WARM</p>\n\n<h3>Meta Ads</h3>\n<p>Interest ads = COLD  \nLookalikes = WARM  \nRetargeting = HOT</p>\n\n<h3>SEO</h3>\n<p>Informational keywords = COLD  \nComparison keywords = WARM  \nTransactional keywords = HOT</p>\n\n<h3>Landing Pages</h3>\n<p>One page must serve ONE temperature only.</p>\n\n<h2>500-Day Click Temperature Optimization Roadmap</h2>\n\n<div class=\"diagram-box\">\nDAY 1–100  \n- Segment clicks by temperature  \n- Rewrite ad messaging for intent  \n- Fix landing page mismatch  \n\nDAY 100–250  \n- Create warm-click nurturing paths  \n- Build trust-based landing modules  \n- Start temperature scoring  \n\nDAY 250–500  \n- Multi-channel temperature mapping  \n- Automated temperature targeting  \n- Predictive conversion modelling  \n</div>\n\n<h2>Conclusion</h2>\n<p>Click Temperature shapes cost, conversion, and growth velocity.  \nBrands that engineer temperature-aligned funnels outperform competitors by a massive margin.</p>\n\n<h2>FAQs</h2>\n\n<h3>1. Can click temperature reduce cost per lead?</h3>\n<p>Yes — temperature mismatch is the biggest reason behind high CPL.</p>\n\n<h3>2. Does this apply to small businesses?</h3>\n<p>More than ever — small budgets need smart segmentation.</p>\n\n<h3>3. How quickly can results appear?</h3>\n<p>Within 7–30 days depending on ad channels and traffic volume.</p>\n\n<h2>Recommended Reading (Related Posts)</h2>\n<ul>\n <li><a href=\"/blog/funnel-velocity-2025-performance-marketing-clarity-framework\">Funnel Velocity 2025</a></li>\n <li><a href=\"/blog/attention-friction-2025-ad-dropoff-reduction-model\">Attention Friction 2025</a></li>\n <li><a href=\"/blog/meta-ads-precision-2025-targeting-readiness-framework\">Meta Ads Precision 2025</a></li>\n</ul>\n\n</body>\n</html>\n",
  "coverImage": "https://ik.imagekit.io/beetlebulbs/blogs/1765001894796-561152625_qlKvH_Y50.jpeg",
  "category": "Digital Marketing 360",
  "date": "2025-11-19"
}