{
  "title": "Signal Density 2025 — Why Your Social Content Isn’t Converting & How to Engineer High-Density Posts That Perform Everywhere",
  "slug": "signal-density-2025-high-density-social-content-framework",
  "description": "A 2025 guide explaining how brands can increase social media signal density to boost visibility, saves, shares, and conversions across platforms.",
  "content": "<!DOCTYPE html>\n<html lang=\"en\">\n<head>\n\n<title>Signal Density 2025 — Why Your Social Content Isn’t Converting & How to Engineer High-Density Posts That Perform Everywhere</title>\n\n<meta name=\"description\" content=\"A 2025 guide explaining how brands improve social content performance using signal density—boosting visibility, saves, shares, and conversions.\">\n\n<meta name=\"keywords\" content=\"signal density 2025, social media performance, digital marketing 2025, content engineering, social media optimization\">\n\n<!-- OG TAGS -->\n<meta property=\"og:title\" content=\"Signal Density 2025 — Why Your Social Content Isn’t Converting\">\n<meta property=\"og:description\" content=\"A 2025 framework showing how to increase social media signal density for higher reach, engagement, and conversions.\">\n<meta property=\"og:type\" content=\"article\">\n<meta property=\"og:image\" content=\"COVER_IMAGE_URL\">\n<meta property=\"og:url\" content=\"https://yourdomain.com/blog/signal-density-2025-high-density-social-content-framework\">\n<meta property=\"article:section\" content=\"Digital Marketing 360\">\n\n<!-- JSON-LD -->\n<script type=\"application/ld+json\">\n{\n \"@context\": \"https://schema.org\",\n \"@type\": \"Article\",\n \"headline\": \"Signal Density 2025 — Why Your Social Content Isn’t Converting & How to Engineer High-Density Posts That Perform Everywhere\",\n \"description\": \"A complete 2025 digital marketing guide showing how high-density content increases reach, saves, shares, and conversions.\",\n \"articleSection\": \"Digital Marketing 360\",\n \"author\": { \"@type\": \"Person\", \"name\": \"BeetleBulbs\" },\n \"publisher\": {\n   \"@type\": \"Organization\",\n   \"name\": \"BeetleBulbs\",\n   \"logo\": { \"@type\": \"ImageObject\", \"url\": \"YOUR_LOGO_URL\" }\n },\n \"datePublished\": \"2025-10-00\"\n}\n</script>\n\n<!-- DIAGRAM CSS -->\n<style>\n.diagram-box{\n background:var(--bb-bg,#f7f7f7);\n color:var(--bb-text,#111);\n padding:14px;\n border-radius:6px;\n white-space:pre;\n overflow-x:auto;\n font-family:monospace;\n font-size:14px;\n line-height:1.6;\n}\n:root{ --bb-bg:#f7f7f7; --bb-text:#111; }\n.dark{ --bb-bg:#1a1a1a; --bb-text:#e6e6e6; }\n@media(max-width:640px){\n .diagram-box{font-size:13px;}\n}\n</style>\n\n</head>\n<body>\n\n<div style=\"margin-bottom:18px;font-size:14px;color:#555;\">\nCategory: <strong>Digital Marketing 360</strong>\n</div>\n\n<h1>Signal Density 2025 — Why Your Social Content Isn’t Converting & How to Engineer High-Density Posts That Perform Everywhere</h1>\n\n<h2>Short Description</h2>\n<p>A 2025 guide explaining how brands can increase social media signal density to boost visibility, saves, shares, and conversions.</p>\n\n<h2>Introduction</h2>\n<p>Every brand is posting. But very few brands are creating content with <strong>signal density</strong>—the invisible factor that determines whether a post gets saved, shared, recommended, or ignored.</p>\n\n<p>Platforms like Instagram, LinkedIn, YouTube, Facebook, and even emerging channels use one hidden rule:</p>\n\n<p><strong>The higher your signal density, the more your content gets pushed.</strong></p>\n\n<p>This single metric determines:</p>\n<ul>\n <li>reach</li>\n <li>save rate</li>\n <li>share rate</li>\n <li>comment depth</li>\n <li>lead generation</li>\n <li>conversion potential</li>\n</ul>\n\n<h2>The Signal Density Framework 2025 (Text Diagram)</h2>\n<div class=\"diagram-box\">\n+--------------------------------------------------------------+\n|                SIGNAL DENSITY MODEL — 2025                   |\n+--------------------------------------------------------------+\n|  1. Information Density                                      |\n|     - value per second                                       |\n+--------------------------------------------------------------+\n|  2. Emotional Density                                        |\n|     - how strongly audience feels the message                |\n+--------------------------------------------------------------+\n|  3. Structural Density                                       |\n|     - clarity, pacing, order                                 |\n+--------------------------------------------------------------+\n|  4. Shareability Density                                     |\n|     - “Would I send this to someone?”                        |\n+--------------------------------------------------------------+\n|  5. Conversion Density                                       |\n|     - micro-psychological nudges                             |\n+--------------------------------------------------------------+\n</div>\n\n<h2>1. Information Density</h2>\n<p>Low-density content feels empty. High-density content feels valuable.</p>\n<ul>\n <li>fast insights</li>\n <li>compressed value</li>\n <li>clear point delivery</li>\n</ul>\n\n<h2>2. Emotional Density</h2>\n<p>Platforms reward high emotional resonance.</p>\n\n<ul>\n <li>empathy</li>\n <li>confidence</li>\n <li>relief</li>\n <li>motivation</li>\n</ul>\n\n<h2>Signal Flow Map 2025 (Text Diagram)</h2>\n<div class=\"diagram-box\">\nVALUE → EMOTION → CLARITY → SAVES → SHARES → REACH → LEADS  \n |         |          |         | \nInfo     Feeling    Structure  Social Proof\n</div>\n\n<h2>3. Structural Density</h2>\n<p>Structure determines comprehension speed.</p>\n\n<ul>\n <li>scan-friendly formatting</li>\n <li>pacing control</li>\n <li>predictable flow</li>\n</ul>\n\n<h2>4. Shareability Density</h2>\n<p>Content should be “share-trigger optimized”.</p>\n\n<ul>\n <li>relatable statements</li>\n <li>contrarian insights</li>\n <li>visually clean ideas</li>\n</ul>\n\n<h2>5. Conversion Density</h2>\n<p>Strategic micro-nudges guide user action.</p>\n\n<ul>\n <li>smart call-to-actions</li>\n <li>contextual CTAs</li>\n <li>solution-oriented framing</li>\n</ul>\n\n<h2>Global Examples (2025)</h2>\n\n<h3>India + USA (D2C)</h3>\n<p>High-shareability visuals increase organic reach 5x.</p>\n\n<h3>UAE + Europe (SaaS)</h3>\n<p>Clarity-structured carousels improve sign-up conversions.</p>\n\n<h3>Australia + UK (Local Businesses)</h3>\n<p>Emotionally dense posts improve community engagement.</p>\n\n<h2>500-Day Signal Density Roadmap</h2>\n<div class=\"diagram-box\">\nDAY 1–100  \n- Remove low-density content  \n- Identify audience resonance  \n- Rewrite content for precision  \n\nDAY 100–250  \n- Create density templates  \n- Build multi-platform creative rhythm  \n- Emotional layering  \n\nDAY 250–500  \n- Message testing  \n- AI-assisted insights (non-AI writing)  \n- Cross-platform density harmonization  \n</div>\n\n<h2>Conclusion</h2>\n<p>Signal Density determines whether your content disappears or dominates.  \nBrands that engineer high-density content outperform competitors—consistently and globally.</p>\n\n<h2>FAQs</h2>\n\n<h3>1. Does higher signal density increase reach?</h3>\n<p>Yes—platform algorithms detect depth and reward it.</p>\n\n<h3>2. Can small brands use this system?</h3>\n<p>Small brands benefit even faster because dense content spreads quicker.</p>\n\n<h3>3. Is this helpful for paid ads?</h3>\n<p>Absolutely—ad performance improves when density is engineered.</p>\n\n<h2>Related Posts</h2>\n<ul>\n <li><a href=\"/blog/multi-channel-resonance-2025-cross-platform-engagement-framework\">Multi-Channel Resonance 2025</a></li>\n <li><a href=\"/blog/algorithmic-clarity-2025-social-platform-visibility-science\">Algorithmic Clarity 2025</a></li>\n <li><a href=\"/blog/message-density-2025-high-retention-content-method\">Message Density 2025</a></li>\n</ul>\n\n</body>\n</html>\n",
  "coverImage": "https://ik.imagekit.io/beetlebulbs/blogs/1764958019198-712673317_-5Su0F3YT.jpeg",
  "category": "Digital Marketing 360",
  "date": "2025-11-14"
}